{
  "sq": "albanian",
  "ar": "arabic",
  "bn": "bengali",
  "pb": "brazilian-portuguese",
  "bg": "bulgarian",
  "zh": "chinese",
  "hr": "croatian",
  "cs": "czech",
  "da": "danish",
  "nl": "dutch",
  "en": "english",
  "et": "estonian",
  "fa": "farsi-persian",
  "fi": "finnish",
  "fr": "french",
  "de": "german",
  "el": "greek",
  "he": "hebrew",
  "hu": "hungarian",
  "id": "indonesian",
  "it": "italian",
  "ja": "japanese",
  "ko": "korean",
  "lt": "lithuanian",
  "mk": "macedonian",
  "ms": "malay",
  "no": "norwegian",
  "pl": "polish",
  "pt": "portuguese",
  "ro": "romanian",
  "ru": "russian",
  "sr": "serbian",
  "sl": "slovenian",
  "es": "spanish",
  "sv": "swedish",
  "th": "thai",
  "tr": "turkish",
  "ur": "urdu",
  "uk": "ukrainian",
  "vi": "vietnamese"
}
